pelt-0.2.0.dist-info/METADATA
pelt-0.2.0.dist-info/WHEEL
pelt-0.2.0.dist-info/licenses/LICENSE
pelt/__init__.py
pelt/pelt.cpython-314-darwin.so
pelt-0.2.0.dist-info/RECORD
