Metadata-Version: 2.4
Name: pelt
Version: 0.2.0
Classifier: Programming Language :: Rust
Classifier: Programming Language :: Python :: Implementation :: CPython
Classifier: Programming Language :: Python :: Implementation :: PyPy
License-File: LICENSE
Summary: Changepoint detection with Pruned Exact Linear Time
Keywords: changepoint
Author-email: Thomas Versteeg <t.versteeg@cemsbv.io>
Requires-Python: >=3.11
Project-URL: repository, https://github.com/cemsbv/pelt
